{
"skeleton": {
	"hash": "A/OcfgsxvMn7OBmk0+07OIWRcdg",
	"spine": "3.8.75",
	"x": -200,
	"y": -269.44,
	"width": 417.36,
	"height": 469.44,
	"images": "F:/Spine图片文件夹/小闪光/",
	"audio": ""
},
"bones": [
	{ "name": "root" },
	{ "name": "Main", "parent": "root", "length": 308.03, "rotation": 0.74, "x": -170, "y": 247 },
	{ "name": "Front_Body", "parent": "Main", "length": 138.06, "rotation": 90.92, "x": 196.52, "y": -346.58 },
	{ "name": "Left_Body", "parent": "Main", "length": 113.02, "rotation": 90.27, "x": 108.25, "y": -249.31 },
	{ "name": "Right_Body", "parent": "Main", "length": 88.01, "rotation": 88.6, "x": 249.55, "y": -215.78 },
	{ "name": "FElec", "parent": "Front_Body", "x": 69.44, "y": 0.12 },
	{ "name": "Front_Elec", "parent": "FElec", "length": 93.42, "rotation": 115.62, "x": 83.01, "y": 4.97 },
	{ "name": "Front_Elec2", "parent": "FElec", "length": 73.93, "rotation": -172.48, "x": -1.04, "y": 76.48 },
	{ "name": "Front_Elec3", "parent": "FElec", "length": 94.96, "rotation": -103.07, "x": -68.32, "y": 47.83 },
	{ "name": "Front_Elec4", "parent": "FElec", "length": 30.35, "rotation": -31.92, "x": -62.91, "y": -52.01 },
	{ "name": "Front_Elec5", "parent": "FElec", "length": 103.25, "rotation": 13.55, "x": -31.93, "y": -84.38 },
	{ "name": "Front_Elec6", "parent": "FElec", "length": 32.96, "rotation": 73.75, "x": 67.32, "y": -38.73 },
	{ "name": "LElec", "parent": "Left_Body", "x": 50.89, "y": -3.41 },
	{ "name": "Left_Elec", "parent": "LElec", "length": 75.3, "rotation": -42.49, "x": 4.99, "y": 64.49 },
	{ "name": "Left_Elec2", "parent": "LElec", "length": 35.46, "rotation": -108.33, "x": 73.82, "y": 3.93 },
	{ "name": "Left_Elec3", "parent": "LElec", "length": 20.24, "rotation": -143.32, "x": 53.34, "y": -41.95 },
	{ "name": "Left_Elec4", "parent": "LElec", "length": 43.95, "rotation": -149.56, "x": 47.58, "y": -59.32 },
	{ "name": "Left_Elec5", "parent": "LElec", "length": 48.33, "rotation": 77.25, "x": -66.94, "y": -8.87 },
	{ "name": "Left_Elec6", "parent": "LElec", "length": 50.65, "rotation": 17.42, "x": -50.85, "y": 56.74 },
	{ "name": "RElec", "parent": "Right_Body", "x": 36.32, "y": -2.01 },
	{ "name": "Right_Elec", "parent": "RElec", "length": 33.3, "rotation": -25.39, "x": -15.9, "y": 48.69 },
	{ "name": "Right_Elec2", "parent": "RElec", "length": 35.73, "rotation": -25.3, "x": 21.2, "y": 44.86 },
	{ "name": "Right_Elec3", "parent": "RElec", "length": 29.27, "rotation": -82.68, "x": 55.64, "y": 21.45 },
	{ "name": "Right_Elec4", "parent": "RElec", "length": 69.01, "rotation": -148.36, "x": 55.57, "y": -17.65 },
	{ "name": "Right_Elec5", "parent": "RElec", "length": 45.27, "rotation": 178.07, "x": -1.02, "y": -34.45 }
],
"slots": [
	{ "name": "Shadow", "bone": "root", "attachment": "Shadow" },
	{ "name": "Left_Body", "bone": "Left_Body", "attachment": "Left_Body" },
	{ "name": "Left_Elec", "bone": "LElec", "attachment": "Left_Elec" },
	{ "name": "Right_Body", "bone": "Right_Body", "attachment": "Right_Body" },
	{ "name": "Right_Elec", "bone": "RElec", "attachment": "Right_Elec" },
	{ "name": "Front_Body", "bone": "Front_Body", "attachment": "Front_Body" },
	{ "name": "Front_Elec", "bone": "FElec", "attachment": "Front_Elec" }
],
"skins": [
	{
		"name": "default",
		"attachments": {
			"Shadow": {
				"Shadow": { "x": 17.36, "y": -69.44, "width": 400, "height": 400 }
			},
			"Right_Elec": {
				"Right_Elec": {
					"type": "mesh",
					"uvs": [ 0.72588, 0.15124, 0.74316, 0.15181, 0.74658, 0.14069, 0.78505, 0.14924, 0.82381, 0.17489, 0.84006, 0.20367, 0.85744, 0.22933, 0.85288, 0.24642, 0.8583, 0.29345, 0.85003, 0.29089, 0.82723, 0.32451, 0.85362, 0.36288, 0.80831, 0.39793, 0.8066, 0.42301, 0.76128, 0.42957, 0.57198, 0.35102, 0.55346, 0.30086, 0.58224, 0.29117, 0.59763, 0.27264, 0.59735, 0.25241, 0.57911, 0.25384, 0.56714, 0.23332, 0.56457, 0.21736, 0.57455, 0.19684, 0.5982, 0.17404, 0.63554, 0.14497, 0.64323, 0.15152, 0.67829, 0.12074, 0.68684, 0.11818, 0.60219, 0.24557, 0.63696, 0.26837, 0.63269, 0.28148, 0.62072, 0.27863, 0.61701, 0.30941, 0.59022, 0.32024, 0.58737, 0.34475, 0.60105, 0.23816, 0.60903, 0.2014, 0.62898, 0.17689, 0.72759, 0.16007, 0.70935, 0.1615, 0.67715, 0.1595, 0.67658, 0.15323, 0.63476, 0.1666, 0.8184, 0.31625, 0.82467, 0.28918, 0.83464, 0.27236, 0.82837, 0.21964, 0.80614, 0.20653, 0.80301, 0.18601, 0.78591, 0.17717, 0.78505, 0.19399, 0.75057, 0.17746, 0.75672, 0.3871, 0.77582, 0.39138, 0.82398, 0.36459, 0.80546, 0.34407, 0.7838, 0.3415, 0.77667, 0.31813, 0.75843, 0.30588, 0.76584, 0.28593, 0.81429, 0.29676 ],
					"triangles": [ 53, 33, 59, 35, 53, 14, 61, 60, 45, 59, 30, 60, 59, 60, 58, 57, 53, 59, 57, 59, 58, 54, 53, 57, 14, 54, 13, 58, 60, 61, 56, 57, 58, 44, 56, 58, 54, 57, 56, 54, 56, 55, 12, 54, 55, 13, 54, 12, 58, 61, 44, 55, 56, 10, 11, 55, 10, 12, 55, 11, 56, 44, 10, 14, 53, 54, 39, 0, 1, 39, 1, 52, 50, 3, 4, 3, 1, 2, 52, 3, 50, 52, 1, 3, 49, 50, 4, 51, 52, 50, 51, 50, 49, 48, 49, 4, 48, 4, 5, 51, 49, 48, 47, 48, 5, 47, 5, 6, 7, 47, 6, 46, 47, 7, 60, 52, 51, 60, 51, 48, 46, 60, 48, 46, 48, 47, 45, 60, 46, 9, 46, 7, 45, 46, 9, 9, 7, 8, 44, 61, 45, 10, 45, 9, 44, 45, 10, 40, 39, 52, 30, 41, 40, 42, 26, 27, 28, 41, 42, 40, 28, 0, 28, 42, 27, 43, 26, 42, 40, 41, 28, 41, 43, 42, 40, 0, 39, 19, 36, 29, 19, 20, 36, 36, 23, 37, 43, 24, 25, 38, 24, 43, 23, 24, 37, 36, 21, 22, 36, 22, 23, 37, 24, 38, 36, 20, 21, 37, 38, 30, 30, 36, 37, 43, 25, 26, 43, 41, 38, 29, 32, 19, 30, 29, 36, 53, 35, 33, 15, 35, 14, 31, 32, 30, 33, 32, 31, 17, 18, 33, 34, 17, 33, 16, 17, 34, 34, 15, 16, 19, 32, 18, 29, 30, 32, 33, 18, 32, 35, 15, 34, 35, 34, 33, 59, 31, 30, 59, 33, 31, 30, 38, 41, 30, 40, 52, 60, 30, 52 ],
					"vertices": [ 2, 22, 32.8, -1.49, 0.5, 23, -5.7, -3.98, 0.5, 1, 23, -1.95, 1.83, 1, 1, 23, -5.06, 5.29, 1, 1, 23, 5.8, 16.72, 1, 1, 23, 22.58, 24.73, 1, 1, 23, 35.79, 24.37, 1, 1, 23, 48.17, 25.05, 1, 1, 23, 53.09, 19.97, 1, 1, 23, 70.33, 12.14, 1, 1, 23, 67.75, 9.83, 1, 2, 23, 74.59, -4.91, 0.5, 24, 8.87, 18.46, 0.5, 1, 24, 23.72, 29.7, 1, 1, 24, 38.55, 12.22, 1, 1, 24, 48.6, 11.99, 1, 1, 24, 52.04, -6, 1, 1, 20, -6.04, -2.11, 1, 1, 20, 8.73, 13.36, 1, 1, 20, 17.27, 4.72, 1, 1, 20, 26.63, 2.44, 1, 2, 20, 33.85, 6.09, 0.5, 21, -1.32, -6.36, 0.5, 1, 21, -5.03, -0.05, 1, 1, 21, 0.26, 7.85, 1, 1, 21, 5.55, 11.57, 1, 1, 21, 14.67, 11.57, 1, 1, 21, 27.02, 7.06, 1, 1, 21, 44.01, -1.28, 1, 2, 21, 43, -5.2, 0.5, 22, -0.05, 2.24, 0.5, 1, 22, 15.31, 12.84, 1, 1, 22, 18.82, 13.46, 1, 2, 20, 37.16, 5.55, 0.5, 21, 1.99, -6.9, 0.5, 1, 20, 35.07, -10.95, 1, 1, 20, 29.61, -11.71, 1, 1, 20, 28.53, -6.91, 1, 1, 20, 16.82, -10.98, 1, 2, 20, 8.22, -3.26, 0.98985, 24, 11.43, -76.33, 0.01015, 1, 20, -1.09, -6.54, 1, 1, 21, 4.45, -5.19, 1, 1, 21, 19.07, -1.63, 1, 1, 21, 31.38, -4.51, 1, 2, 22, 33.07, -5.08, 0.5, 23, -2.32, -5.21, 0.5, 1, 22, 25.76, -4.8, 1, 1, 22, 13.05, -2.51, 1, 1, 22, 13.12, 0.01, 1, 2, 21, 36.09, -4.79, 0.5, 22, -4.12, -3.36, 0.5, 2, 23, 69.93, -6.24, 0.5, 24, 5.73, 14.78, 0.5, 1, 23, 61.94, 1.49, 1, 1, 23, 58.23, 8.37, 1, 1, 23, 38.86, 17.08, 1, 1, 23, 29.79, 12.16, 1, 1, 23, 22.1, 15.31, 1, 1, 23, 15.55, 11.26, 1, 1, 23, 21.14, 7.51, 1, 1, 23, 8.37, -0.92, 1, 1, 24, 35.15, -8.59, 1, 1, 24, 36.51, -0.88, 1, 1, 24, 24.94, 17.88, 1, 1, 24, 17.08, 10.11, 1, 1, 24, 16.44, 1.41, 1, 1, 24, 7.23, -1.86, 1, 1, 24, 2.66, -9.37, 1, 1, 24, -5.44, -6.77, 1, 1, 24, -1.99, 12.79, 1 ],
					"hull": 29,
					"edges": [ 30, 32, 32, 34, 34, 36, 36, 38, 38, 58, 58, 60, 60, 62, 62, 64, 64, 66, 66, 68, 68, 70, 70, 30, 58, 72, 72, 74, 74, 76, 52, 50, 50, 48, 48, 46, 46, 44, 44, 42, 42, 40, 40, 38, 52, 54, 54, 56, 56, 0, 0, 78, 78, 80, 80, 82, 82, 84, 76, 86, 86, 52, 84, 86, 0, 2, 2, 4, 4, 6, 6, 8, 8, 10, 10, 12, 12, 14, 14, 16, 16, 18, 18, 20, 20, 88, 88, 90, 90, 92, 92, 94, 94, 96, 96, 98, 98, 100, 100, 102, 102, 104, 104, 78, 20, 22, 22, 24, 24, 26, 26, 28, 28, 106, 106, 108, 108, 110, 110, 112, 112, 114, 114, 116, 116, 118, 118, 120, 120, 122, 122, 88, 106, 70, 30, 28 ],
					"width": 400,
					"height": 400
				}
			},
			"Left_Body": {
				"Left_Body": { "x": -7.26, "y": -70.88, "rotation": -91.01, "width": 400, "height": 400 }
			},
			"Front_Elec": {
				"Front_Elec": {
					"type": "mesh",
					"uvs": [ 0.57902, 0.36685, 0.59347, 0.35255, 0.665, 0.37567, 0.70113, 0.354, 0.78494, 0.42553, 0.85339, 0.51512, 0.83389, 0.53101, 0.831, 0.56425, 0.85267, 0.57869, 0.82883, 0.62494, 0.77392, 0.66395, 0.75586, 0.69386, 0.71323, 0.73865, 0.68939, 0.75599, 0.71756, 0.77044, 0.68505, 0.81451, 0.63375, 0.82029, 0.59691, 0.81379, 0.57668, 0.84125, 0.51454, 0.81668, 0.47914, 0.76972, 0.44897, 0.72609, 0.43308, 0.76727, 0.41141, 0.8005, 0.33699, 0.70513, 0.32181, 0.6719, 0.34421, 0.65673, 0.31965, 0.64517, 0.34783, 0.60182, 0.33265, 0.59026, 0.33265, 0.55124, 0.37095, 0.54763, 0.36806, 0.58664, 0.40563, 0.5852, 0.40813, 0.54729, 0.3926, 0.5222, 0.35316, 0.4971, 0.29819, 0.47559, 0.31373, 0.45528, 0.34241, 0.42899, 0.38065, 0.39075, 0.47864, 0.34175, 0.5599, 0.331, 0.42964, 0.54729, 0.42964, 0.521, 0.40933, 0.49471, 0.37467, 0.47559, 0.39977, 0.45647, 0.43323, 0.43974, 0.46908, 0.42421, 0.49656, 0.41943, 0.51927, 0.40509, 0.54078, 0.39075, 0.56468, 0.39672, 0.59933, 0.40509, 0.43164, 0.6271, 0.41791, 0.71453, 0.37528, 0.69141, 0.37962, 0.65095, 0.37167, 0.63216, 0.6744, 0.40674, 0.74881, 0.4407, 0.78638, 0.50645, 0.7573, 0.65673, 0.78042, 0.60904, 0.79559, 0.5498, 0.6995, 0.74082, 0.68939, 0.72276, 0.6865, 0.67868, 0.71251, 0.65845, 0.73346, 0.62233, 0.74574, 0.62811, 0.67422, 0.74082, 0.6771, 0.71192, 0.64965, 0.72926, 0.43362, 0.68446, 0.46035, 0.68013, 0.50515, 0.70614, 0.49865, 0.73648, 0.55717, 0.78706, 0.60702, 0.76972, 0.6417, 0.78923, 0.64459, 0.76827 ],
					"triangles": [ 68, 74, 77, 77, 74, 80, 80, 79, 77, 19, 79, 18, 18, 79, 17, 16, 81, 15, 16, 17, 81, 19, 20, 79, 15, 81, 13, 13, 81, 82, 15, 13, 14, 17, 80, 81, 17, 79, 80, 20, 78, 79, 20, 21, 78, 81, 80, 82, 78, 77, 79, 72, 74, 73, 72, 73, 67, 13, 82, 72, 82, 80, 74, 82, 74, 72, 50, 77, 76, 21, 75, 76, 78, 21, 77, 21, 76, 77, 73, 74, 68, 75, 55, 76, 13, 72, 66, 68, 50, 70, 69, 70, 71, 63, 69, 71, 73, 68, 67, 11, 67, 68, 11, 69, 63, 11, 63, 10, 11, 68, 69, 69, 68, 70, 71, 70, 64, 13, 66, 12, 72, 67, 66, 66, 67, 12, 12, 67, 11, 10, 64, 9, 10, 63, 64, 63, 71, 64, 9, 7, 8, 9, 64, 7, 65, 64, 70, 70, 60, 61, 64, 65, 7, 65, 70, 62, 62, 70, 61, 7, 65, 6, 65, 62, 6, 6, 62, 5, 61, 4, 62, 5, 62, 4, 4, 61, 3, 61, 60, 3, 60, 2, 3, 54, 2, 60, 0, 1, 54, 54, 1, 2, 54, 60, 70, 50, 55, 49, 54, 70, 50, 54, 50, 53, 50, 51, 53, 51, 52, 53, 44, 48, 49, 43, 34, 44, 34, 35, 44, 49, 43, 44, 36, 46, 35, 35, 45, 44, 35, 46, 45, 44, 45, 48, 37, 38, 36, 36, 38, 46, 46, 47, 45, 45, 47, 48, 38, 39, 46, 46, 39, 47, 39, 40, 47, 47, 40, 48, 48, 40, 49, 50, 49, 41, 49, 40, 41, 50, 41, 51, 51, 41, 52, 53, 0, 54, 53, 52, 0, 52, 42, 0, 52, 41, 42, 68, 77, 50, 23, 24, 56, 23, 56, 22, 56, 24, 57, 22, 56, 21, 56, 75, 21, 56, 57, 75, 24, 26, 57, 24, 25, 26, 57, 58, 75, 57, 26, 58, 58, 55, 75, 50, 76, 55, 26, 59, 58, 59, 26, 28, 58, 59, 55, 26, 27, 28, 59, 33, 55, 55, 33, 43, 33, 34, 43, 28, 32, 59, 59, 32, 33, 49, 55, 43, 28, 29, 32, 29, 30, 32, 32, 30, 31 ],
					"vertices": [ 2, 6, -8.07, 6.4, 0.5, 11, 36.06, -3.46, 0.5, 1, 11, 31.91, -10.45, 1, 2, 11, 1.89, -8.71, 0.5, 10, 115.68, 18.43, 0.5, 1, 10, 120.26, 2.21, 1, 1, 10, 83.85, -22.63, 1, 1, 10, 42.09, -39.65, 1, 1, 10, 38, -30.45, 1, 1, 10, 25.47, -25.85, 1, 1, 10, 17.62, -32.7, 1, 1, 10, 2.28, -18.64, 1, 2, 10, -7.02, 6.65, 0.5, 9, 33.75, -11.45, 0.5, 2, 10, -16.67, 16.76, 0.00416, 9, 19.77, -11.23, 0.99584, 2, 9, -4.3, -5.53, 0.5, 8, 99.87, 22, 0.5, 2, 9, -15.09, -0.79, 0.5, 8, 91.9, 13.32, 0.5, 1, 8, 104.09, 9.88, 1, 1, 8, 94.83, -9.97, 1, 1, 8, 75.17, -16.3, 1, 1, 8, 60.21, -16.67, 1, 1, 8, 54.45, -29.03, 1, 1, 8, 28.14, -24.32, 1, 1, 8, 10.55, -8.71, 1, 2, 7, 63.16, 17.28, 0.5, 8, -4.74, 6.01, 0.5, 1, 7, 78.41, 8.37, 1, 1, 7, 90.15, -2.31, 1, 1, 7, 47.74, -25.6, 1, 1, 7, 33.65, -29.47, 1, 1, 7, 29.08, -19.66, 1, 1, 7, 22.95, -28.62, 1, 1, 7, 7.63, -14.73, 1, 1, 7, 2.1, -19.98, 1, 1, 7, -13.31, -17.49, 1, 1, 7, -12.29, -2.14, 1, 1, 7, 2.93, -5.77, 1, 1, 7, 4.76, 9.16, 1, 2, 7, -10.05, 12.57, 0.5, 6, 85.76, 39.21, 0.5, 1, 6, 86.68, 27.44, 1, 1, 6, 96.1, 11.29, 1, 1, 6, 111.7, -6.43, 1, 1, 6, 102.45, -10.81, 1, 1, 6, 87.43, -14.89, 1, 1, 6, 66.83, -21.48, 1, 1, 6, 23.01, -20.93, 1, 1, 6, -7.85, -9.85, 1, 2, 7, -8.67, 21.06, 0.5, 6, 78.12, 43.16, 0.5, 1, 6, 73.3, 33.81, 1, 1, 6, 75.7, 20.74, 1, 1, 6, 84.51, 7.59, 1, 1, 6, 72.08, 5.39, 1, 1, 6, 57.12, 5.58, 1, 1, 6, 41.53, 6.63, 1, 1, 6, 30.88, 9.97, 1, 1, 6, 20.18, 9.04, 1, 1, 6, 9.9, 7.88, 1, 1, 6, 2.5, 14.39, 1, 2, 6, -8.28, 23.72, 0.5, 11, 24.35, 9.29, 0.5, 1, 7, 22.97, 16.75, 1, 1, 7, 56.61, 5.75, 1, 1, 7, 44.76, -9.61, 1, 1, 7, 29.06, -5.31, 1, 1, 7, 21.14, -7.25, 1, 2, 11, -4.88, 2.37, 0.5, 10, 102.7, 18.07, 0.5, 1, 10, 81.79, -7.09, 1, 1, 10, 52.47, -14.69, 1, 2, 10, -2.49, 12.3, 0.5, 9, 32.89, -4.25, 0.5, 1, 10, 13.49, -1.62, 1, 1, 10, 34.77, -13.7, 1, 1, 9, -7.81, -1.23, 1, 2, 9, -3.61, 5.91, 0.5, 8, 89.26, 26.35, 0.5, 1, 9, 11.04, 15.79, 1, 1, 9, 23.27, 10.88, 1, 1, 9, 39.97, 10.92, 1, 1, 9, 40.45, 5.51, 1, 2, 9, -12.91, 7.51, 0.5, 8, 84.75, 18.06, 0.5, 1, 8, 83.59, 29.62, 1, 1, 8, 74.2, 20.65, 1, 1, 8, -14.05, 21.12, 1, 1, 8, -3.91, 24.93, 1, 1, 8, 15.71, 18.28, 1, 1, 8, 15.56, 5.87, 1, 1, 8, 42.51, -9.33, 1, 1, 8, 60.69, 1.41, 1, 1, 8, 75.83, -3.49, 1, 1, 8, 75.3, 4.95, 1 ],
					"hull": 43,
					"edges": [ 0, 84, 84, 82, 82, 80, 80, 78, 78, 76, 76, 74, 74, 72, 72, 70, 70, 68, 68, 86, 86, 88, 88, 90, 90, 92, 92, 94, 94, 96, 96, 98, 98, 100, 100, 102, 102, 104, 104, 106, 106, 108, 0, 108, 68, 66, 86, 110, 66, 64, 64, 62, 62, 60, 60, 58, 58, 56, 56, 54, 54, 52, 52, 50, 50, 48, 48, 46, 46, 44, 44, 42, 42, 112, 112, 114, 114, 116, 116, 118, 118, 110, 0, 2, 2, 4, 4, 120, 108, 120, 4, 6, 6, 8, 120, 122, 122, 124, 8, 10, 10, 12, 12, 14, 14, 16, 16, 18, 18, 20, 20, 126, 126, 128, 128, 130, 130, 124, 20, 22, 22, 24, 24, 132, 132, 134, 134, 136, 136, 138, 138, 140, 140, 142, 142, 126, 24, 26, 134, 144, 144, 146, 146, 148, 26, 28, 28, 30, 30, 32, 32, 34, 34, 36, 36, 38, 38, 40, 40, 42, 42, 150, 150, 152, 152, 154, 154, 156, 156, 158, 158, 160, 160, 162, 162, 164, 164, 148 ],
					"width": 400,
					"height": 400
				}
			},
			"Right_Body": {
				"Right_Body": { "x": -45.86, "y": 75.48, "rotation": -89.35, "width": 400, "height": 400 }
			},
			"Front_Body": {
				"Front_Body": { "x": 97.86, "y": 28.18, "rotation": -91.66, "width": 400, "height": 400 }
			},
			"Left_Elec": {
				"Left_Elec": {
					"type": "mesh",
					"uvs": [ 0.21693, 0.18476, 0.3076, 0.22033, 0.31946, 0.2008, 0.28322, 0.15857, 0.31854, 0.15757, 0.32601, 0.16802, 0.32899, 0.14613, 0.36879, 0.12971, 0.41605, 0.22921, 0.43595, 0.20633, 0.45486, 0.21777, 0.47774, 0.21379, 0.54341, 0.28642, 0.54242, 0.3307, 0.51207, 0.35607, 0.37924, 0.52003, 0.32451, 0.55684, 0.31257, 0.51555, 0.29068, 0.51157, 0.27178, 0.53595, 0.22551, 0.50311, 0.20362, 0.49067, 0.17825, 0.5046, 0.1474, 0.45784, 0.13447, 0.38869, 0.14927, 0.36193, 0.17229, 0.1457, 0.21414, 0.3961, 0.20716, 0.30682, 0.19112, 0.33403, 0.18763, 0.27823, 0.20577, 0.21964, 0.36619, 0.26986, 0.36689, 0.24754, 0.22999, 0.4449, 0.18571, 0.42948, 0.2474, 0.47824, 0.26382, 0.49465, 0.28969, 0.48072, 0.35635, 0.49565, 0.35436, 0.20334, 0.36232, 0.18294, 0.40262, 0.23866, 0.42899, 0.24662, 0.44093, 0.23667, 0.45486, 0.271, 0.47376, 0.2705, 0.49814, 0.29289, 0.47625, 0.35558, 0.5066, 0.29737, 0.51655, 0.29538, 0.52152, 0.31976 ],
					"triangles": [ 38, 36, 34, 37, 36, 38, 39, 38, 32, 17, 18, 38, 37, 38, 18, 39, 17, 38, 15, 39, 48, 19, 37, 18, 16, 17, 39, 16, 39, 15, 20, 37, 19, 20, 36, 37, 20, 21, 36, 21, 34, 36, 21, 35, 34, 35, 25, 27, 24, 25, 35, 23, 24, 35, 23, 35, 21, 22, 23, 21, 35, 27, 34, 38, 34, 27, 15, 48, 14, 46, 10, 11, 48, 47, 49, 51, 48, 49, 14, 48, 51, 14, 51, 13, 46, 11, 12, 50, 47, 46, 12, 50, 46, 51, 50, 12, 13, 51, 12, 49, 47, 50, 51, 49, 50, 47, 48, 45, 45, 32, 43, 44, 9, 10, 44, 10, 46, 45, 44, 46, 8, 9, 44, 43, 8, 44, 43, 44, 45, 47, 45, 46, 33, 40, 42, 8, 41, 7, 5, 6, 41, 5, 3, 4, 40, 2, 5, 2, 3, 5, 41, 40, 5, 42, 40, 41, 8, 42, 41, 41, 6, 7, 42, 8, 43, 43, 32, 42, 2, 40, 33, 25, 29, 27, 29, 28, 27, 31, 26, 0, 31, 0, 1, 32, 1, 33, 31, 1, 32, 30, 26, 31, 28, 30, 31, 32, 28, 31, 30, 25, 26, 27, 28, 32, 29, 30, 28, 25, 30, 29, 33, 1, 2, 32, 33, 42, 27, 32, 38, 45, 48, 32, 48, 39, 32 ],
					"vertices": [ 1, 13, 62.06, 28.39, 1, 1, 13, 75.42, -8.2, 1, 2, 13, 84.41, -6.59, 0.5, 14, 4.71, -10.06, 0.5, 1, 14, -14.16, 1.76, 1, 1, 14, -0.79, 6.34, 1, 1, 14, 3.31, 3.24, 1, 1, 14, 1.84, 11.96, 1, 1, 14, 15.08, 22.97, 1, 2, 14, 44.98, -9.4, 0.5, 15, -1.58, -6.47, 0.5, 1, 15, -3.95, 5.42, 1, 2, 15, 4.29, 8.61, 0.5, 16, -10.44, -3.03, 0.5, 1, 16, -7.03, 5.61, 1, 1, 16, 31.47, 12.86, 1, 1, 16, 46.37, 3.27, 1, 1, 16, 48.69, -12.38, 1, 1, 17, -9.55, -3.83, 1, 1, 17, 8.89, 15.04, 1, 3, 13, -11.75, -87.9, 2.0E-4, 15, 63.74, -109.26, 1.2E-4, 17, 16.93, -0.16, 0.99969, 2, 18, -22.07, -35.43, 0, 17, 25.82, 0.06, 1, 1, 17, 31.24, 11.14, 1, 1, 17, 52.03, 2.05, 1, 2, 18, -3.12, -5.03, 0.5, 17, 61.62, -1.04, 0.5, 1, 18, -5.2, 6.36, 1, 1, 18, 16.45, 12.14, 1, 1, 18, 44.33, 8.31, 1, 2, 13, -8.96, 1.74, 0.5, 18, 52.61, -0.7, 0.5, 1, 13, 61.94, 52.12, 1, 2, 13, -2.02, -26.75, 0.5, 18, 31.43, -20.99, 0.5, 1, 13, 22.89, -1.01, 1, 1, 13, 10.48, -3.41, 1, 1, 13, 26.28, 12.42, 1, 1, 13, 48.65, 22.5, 1, 1, 13, 76.09, -38.88, 1, 1, 13, 82.97, -33.18, 1, 1, 18, 10.91, -20.83, 1, 1, 18, 22.36, -5.98, 1, 1, 17, 45.49, -9.48, 1, 1, 17, 37.72, -4.38, 1, 1, 17, 28.72, -11.94, 1, 1, 17, 1.4, -11.52, 1, 1, 14, 18.34, -6.87, 1, 1, 14, 18.95, 1.87, 1, 1, 14, 40.98, -14.61, 1, 1, 15, 7.1, -6.64, 1, 1, 15, 6.87, -0.42, 1, 1, 15, 21.14, -4.41, 1, 2, 15, 25.61, 1.69, 0.5, 16, 11.5, -7.59, 0.5, 1, 16, 24.22, -3.94, 1, 1, 16, 41.04, -24.49, 1, 1, 16, 27.52, -1.99, 1, 1, 16, 28.91, 1.82, 1, 1, 16, 38.27, -1.57, 1 ],
					"hull": 27,
					"edges": [ 50, 54, 54, 56, 56, 58, 58, 60, 60, 62, 62, 64, 64, 66, 66, 4, 4, 2, 2, 0, 0, 52, 52, 50, 50, 48, 48, 46, 46, 44, 54, 68, 68, 70, 70, 42, 44, 42, 42, 72, 72, 74, 74, 76, 76, 78, 78, 30, 30, 32, 32, 34, 34, 36, 36, 38, 42, 40, 40, 38, 4, 6, 6, 8, 8, 10, 10, 12, 12, 14, 14, 16, 4, 80, 80, 82, 82, 84, 84, 16, 16, 18, 16, 86, 86, 88, 88, 90, 18, 20, 20, 92, 90, 92, 20, 22, 22, 24, 92, 94, 24, 26, 26, 28, 28, 96, 94, 98, 98, 100, 100, 102, 102, 96, 78, 96, 30, 28 ],
					"width": 400,
					"height": 400
				}
			}
		}
	}
],
"animations": {
	"Attack": {
		"slots": {
			"Front_Elec": {
				"color": [
					{ "color": "ffffff00" },
					{ "time": 0.5, "color": "ffffffff" }
				]
			},
			"Left_Elec": {
				"color": [
					{ "color": "ffffff6d" },
					{ "time": 0.5, "color": "ffffffff" }
				]
			},
			"Right_Elec": {
				"color": [
					{ "color": "ffffffa5" },
					{ "time": 0.5, "color": "ffffffff" }
				]
			}
		},
		"bones": {
			"RElec": {
				"rotate": [
					{},
					{ "time": 0.8333, "angle": 180 },
					{ "time": 1.6667 }
				],
				"translate": [
					{},
					{ "time": 0.8333, "x": 9.6, "y": -8.56 },
					{ "time": 1.6667 }
				]
			},
			"FElec": {
				"rotate": [
					{},
					{ "time": 0.8333, "angle": 180 },
					{ "time": 1.6667 }
				]
			},
			"LElec": {
				"rotate": [
					{},
					{ "time": 0.8333, "angle": 180 },
					{ "time": 1.6667 }
				]
			},
			"Front_Body": {
				"translate": [
					{},
					{ "time": 0.5, "y": 41.29 }
				],
				"scale": [
					{},
					{ "time": 1, "x": 0.727, "y": 0.781 },
					{ "time": 1.1667 }
				]
			},
			"Left_Body": {
				"translate": [
					{},
					{ "time": 0.5, "x": 28.63, "curve": "stepped" },
					{ "time": 1, "x": 28.63 },
					{ "time": 1.3333, "x": 381.36, "y": -177.03 },
					{ "time": 1.6667 }
				],
				"scale": [
					{},
					{ "time": 0.8333, "x": 0.899, "y": 0.932 },
					{ "time": 1 }
				]
			},
			"Right_Body": {
				"translate": [
					{},
					{ "time": 0.5, "x": -20.21, "y": 4.13, "curve": "stepped" },
					{ "time": 1.1667, "x": -20.21, "y": 4.13 },
					{ "time": 1.5, "x": 310.95, "y": -62.5 },
					{ "time": 1.6667 }
				],
				"scale": [
					{},
					{ "time": 0.8333, "x": 0.89, "y": 0.882 },
					{ "time": 1.1667 }
				]
			}
		}
	},
	"Idle": {
		"slots": {
			"Front_Elec": {
				"color": [
					{ "color": "ffffff00" },
					{ "time": 1.6667, "color": "ffffff77", "curve": "stepped" },
					{ "time": 2.3333, "color": "ffffff77" },
					{ "time": 4, "color": "ffffff00" }
				]
			},
			"Left_Elec": {
				"color": [
					{ "color": "ffffff6d" },
					{ "time": 1.6667, "color": "ffffffc9", "curve": "stepped" },
					{ "time": 2.3333, "color": "ffffffc9" },
					{ "time": 4, "color": "ffffff6d" }
				]
			},
			"Right_Elec": {
				"color": [
					{ "color": "ffffffa5" },
					{ "time": 1.6667, "color": "ffffff29", "curve": "stepped" },
					{ "time": 2.3333, "color": "ffffff29" },
					{ "time": 4, "color": "ffffffa5" }
				]
			}
		},
		"bones": {
			"LElec": {
				"rotate": [
					{},
					{ "time": 2, "angle": 180 },
					{ "time": 4 }
				]
			},
			"RElec": {
				"rotate": [
					{},
					{ "time": 2, "angle": 180 },
					{ "time": 4 }
				]
			},
			"Front_Body": {
				"translate": [
					{},
					{ "time": 1, "y": -10.6 },
					{ "time": 2 },
					{ "time": 3, "y": -10.6 },
					{ "time": 4 }
				]
			},
			"FElec": {
				"rotate": [
					{},
					{ "time": 2, "angle": 180 },
					{ "time": 4 }
				]
			},
			"Left_Body": {
				"translate": [
					{},
					{ "time": 1, "y": -30.02 },
					{ "time": 2 },
					{ "time": 3, "y": -30.02 },
					{ "time": 4 }
				]
			},
			"Right_Body": {
				"translate": [
					{},
					{ "time": 1, "y": 22.11 },
					{ "time": 2 },
					{ "time": 3, "y": 22.11 },
					{ "time": 4 }
				]
			}
		}
	}
}
}